binarycookies/__init__.py
binarycookies/__main__.py
binarycookies/_deserialize.py
binarycookies/_serialize.py
binarycookies/models.py
binarycookies/parser.py
binarycookies/py.typed
binary_cookies_parser-2.1.2.dist-info/LICENSE
binary_cookies_parser-2.1.2.dist-info/METADATA
binary_cookies_parser-2.1.2.dist-info/WHEEL
binary_cookies_parser-2.1.2.dist-info/entry_points.txt
binary_cookies_parser-2.1.2.dist-info/RECORD
