Metadata-Version: 2.3
Name: binary-cookies-parser
Version: 2.1.2
Summary: Python Binary Cookies (de)serializer
Author: Daniel Tom
Author-email: d.e.tom89@gmail.com
Requires-Python: >=3.8,<4.0
Classifier: Programming Language :: Python :: 3
Classifier: Programming Language :: Python :: 3.8
Classifier: Programming Language :: Python :: 3.9
Classifier: Programming Language :: Python :: 3.10
Classifier: Programming Language :: Python :: 3.11
Classifier: Programming Language :: Python :: 3.12
Classifier: Programming Language :: Python :: 3.13
Requires-Dist: pydantic (>=2.0.0,<3.0.0)
Requires-Dist: typer (>=0.12.3,<0.17.0)
